d4d_analytics/__init__.py
d4d_analytics-0.1.0.dist-info/METADATA
d4d_analytics-0.1.0.dist-info/WHEEL
d4d_analytics-0.1.0.dist-info/top_level.txt
d4d_analytics-0.1.0.dist-info/RECORD
