Metadata-Version: 2.1
Name: d4d-analytics
Version: 0.1.0
Summary: Institutional-grade analytics infrastructure for Ethereum microcaps.
Home-page: https://d4d.com
Author: Crypto Underground
Author-email: x@d4d.com
License: MIT
Platform: UNKNOWN
Classifier: Development Status :: 3 - Alpha
Classifier: Intended Audience :: Developers
Classifier: Programming Language :: Python :: 3
Requires-Dist: requests
